baresql/__init__.py
baresql/baresql.py
baresql-0.7.4.dist-info/DESCRIPTION.rst
baresql-0.7.4.dist-info/METADATA
baresql-0.7.4.dist-info/RECORD
baresql-0.7.4.dist-info/WHEEL
baresql-0.7.4.dist-info/metadata.json
baresql-0.7.4.dist-info/top_level.txt
