Metadata-Version: 1.1
Name: baresql
Version: 0.7.4
Summary: playing SQL directly on Python datas
Home-page: https://github.com/stonebig/baresql
Author: stonebig
Author-email: write_pull_requests_to_stonebig@github.com
License: MIT license
Keywords: sqlite,sql
Platform: UNKNOWN
Classifier: Development Status :: 5 - Production/Stable
Classifier: Environment :: Console
Classifier: Intended Audience :: Education
Classifier: License :: OSI Approved :: MIT License
Classifier: Operating System :: OS Independent
Classifier: Programming Language :: Python
Classifier: Programming Language :: Python :: 2.7
Classifier: Programming Language :: Python :: 3
Classifier: Programming Language :: Python :: 3.3
Classifier: Programming Language :: Python :: 3.4
Classifier: Topic :: Scientific/Engineering :: Information Analysis
